django_firebird/__init__.py
django_firebird/_version.py
django_firebird/base.py
django_firebird/client.py
django_firebird/compiler.py
django_firebird/creation.py
django_firebird/expressions.py
django_firebird/features.py
django_firebird/introspection.py
django_firebird/operations.py
django_firebird/py.typed
django_firebird/schema.py
django_firebird/management/__init__.py
django_firebird/management/commands/__init__.py
django_firebird/management/commands/inspectdb_firebird.py
django_firebird_backend-0.1.1.dist-info/METADATA
django_firebird_backend-0.1.1.dist-info/WHEEL
django_firebird_backend-0.1.1.dist-info/licenses/LICENSE
django_firebird_backend-0.1.1.dist-info/RECORD
