Metadata-Version: 2.4
Name: django-firebird-backend
Version: 0.1.1
Summary: Firebird database backend for Django 5.0+
Project-URL: Homepage, https://github.com/joseanoxp/django-firebird-backend
Project-URL: Documentation, https://github.com/joseanoxp/django-firebird-backend#readme
Project-URL: Repository, https://github.com/joseanoxp/django-firebird-backend
Project-URL: Issues, https://github.com/joseanoxp/django-firebird-backend/issues
Project-URL: Changelog, https://github.com/joseanoxp/django-firebird-backend/blob/main/CHANGELOG.md
Author-email: joseanoxp <joseanodev@gmail.com>
License-Expression: BSD-3-Clause
License-File: LICENSE
Keywords: backend,database,django,firebird,sql
Classifier: Development Status :: 4 - Beta
Classifier: Environment :: Web Environment
Classifier: Framework :: Django
Classifier: Framework :: Django :: 5.0
Classifier: Framework :: Django :: 5.1
Classifier: Framework :: Django :: 6.0
Classifier: Intended Audience :: Developers
Classifier: License :: OSI Approved :: BSD License
Classifier: Operating System :: OS Independent
Classifier: Programming Language :: Python
Classifier: Programming Language :: Python :: 3
Classifier: Programming Language :: Python :: 3 :: Only
Classifier: Programming Language :: Python :: 3.11
Classifier: Programming Language :: Python :: 3.12
Classifier: Programming Language :: Python :: 3.13
Classifier: Programming Language :: Python :: 3.14
Classifier: Topic :: Database
Classifier: Topic :: Internet :: WWW/HTTP
Classifier: Topic :: Software Development :: Libraries :: Python Modules
Requires-Python: >=3.11
Requires-Dist: django>=5.0
Requires-Dist: firebird-driver>=1.10.0
Provides-Extra: dev
Requires-Dist: pytest-cov>=4.0; extra == 'dev'
Requires-Dist: pytest-django>=4.5; extra == 'dev'
Requires-Dist: pytest>=8.0; extra == 'dev'
